pro_gan_pth-1.0.dist-info/DESCRIPTION.rst
pro_gan_pth-1.0.dist-info/METADATA
pro_gan_pth-1.0.dist-info/RECORD
pro_gan_pth-1.0.dist-info/WHEEL
pro_gan_pth-1.0.dist-info/metadata.json
pro_gan_pth-1.0.dist-info/top_level.txt
pro_gan_pytorch/PRO_GAN.py
pro_gan_pytorch/__init__.py
