Metadata-Version: 2.0
Name: pro-gan-pth
Version: 1.0
Summary: ProGAN package implemented as an extension of PyTorch nn.Module
Home-page: https://github.com/akanimax/pro_gan_pytorch
Author: akanimax
Author-email: akanimax@gmail.com
License: MIT
Platform: UNKNOWN
